{
    "classifiers": [
        "Intended Audience :: Developers",
        "Intended Audience :: Science/Research",
        "License :: OSI Approved :: MIT License",
        "Natural Language :: English",
        "Operating System :: Unix",
        "Operating System :: POSIX",
        "Topic :: Utilities"
    ],
    "entry_points": {
        "console_scripts": [
            "myapps=myapps.cli:main"
        ]
    },
    "author": "Daniela Varela T",
    "license": "MIT",
    "name": "myapps",
    "long_description": "📘 learn more on `GitHub <https://github.com/danielavarelat/myapps>`_!",
    "description": "myapps Isabl applications and logic.",
    "url": "https://github.com/danielavarelat/myapps"
}
